zeroizepy/__init__.py
zeroizepy/_sodium.py
zeroizepy/crypto.py
zeroizepy/file.py
zeroizepy/memory.py
zeroizepy/os_erase.py
zeroizepy/session.py
zeroizepy/utils.py
zeroizepy-1.2.0.dist-info/licenses/LICENSE.txt
zeroizepy-1.2.0.dist-info/METADATA
zeroizepy-1.2.0.dist-info/WHEEL
zeroizepy-1.2.0.dist-info/entry_points.txt
zeroizepy-1.2.0.dist-info/top_level.txt
zeroizepy-1.2.0.dist-info/RECORD
