Metadata-Version: 2.4
Name: zeroizepy
Version: 1.2.0
Summary: A Python library for secure file deletion, in-memory secret handling and cryptographic erasure.
Home-page: https://github.com/xavenordu/Xavpy-library
Author: Ordu Stephen Chinedu
Author-email: Ordu Stephen Chinedu <fordstphn@gmail.com>
License: MIT License
Project-URL: Homepage, https://github.com/xavenordu/Xavpy-library
Project-URL: Documentation, https://github.com/xavenordu/Xavpy-library
Project-URL: Repository, https://github.com/xavenordu/Xavpy-library
Project-URL: Bug Tracker, https://github.com/xavenordu/Xavpy-library/issues
Project-URL: Changelog, https://github.com/xavenordu/Xavpy-library/blob/main/CHANGELOG.md
Keywords: security,privacy,encryption,secure deletion,data sanitization,cryptography
Classifier: Development Status :: 5 - Production/Stable
Classifier: Programming Language :: Python :: 3
Classifier: Programming Language :: Python :: 3 :: Only
Classifier: License :: OSI Approved :: MIT License
Classifier: Topic :: Security :: Cryptography
Classifier: Topic :: System :: Archiving
Requires-Python: >=3.8
License-File: LICENSE.txt
Requires-Dist: psutil>=5.9.0
Requires-Dist: cryptography>=41.0.0
Provides-Extra: crypto
Requires-Dist: pynacl>=1.5.0; extra == "crypto"
Provides-Extra: dev
Requires-Dist: pytest>=7.4.0; extra == "dev"
Requires-Dist: hypothesis>=6.0.0; extra == "dev"
Requires-Dist: cryptography>=41.0.0; extra == "dev"
Dynamic: license-file
